philote_mdo/__init__.py
philote_mdo/csdl/__init__.py
philote_mdo/csdl/explicit.py
philote_mdo/csdl/implicit.py
philote_mdo/examples/__init__.py
philote_mdo/examples/paraboloid.py
philote_mdo/examples/quadratic.py
philote_mdo/examples/rosenbrock.py
philote_mdo/examples/sellar.py
philote_mdo/general/__init__.py
philote_mdo/general/discipline.py
philote_mdo/general/discipline_client.py
philote_mdo/general/discipline_server.py
philote_mdo/general/explicit_client.py
philote_mdo/general/explicit_discipline.py
philote_mdo/general/explicit_server.py
philote_mdo/general/implicit_client.py
philote_mdo/general/implicit_discipline.py
philote_mdo/general/implicit_server.py
philote_mdo/general/run_server.py
philote_mdo/generated/__init__.py
philote_mdo/generated/data_pb2.py
philote_mdo/generated/data_pb2.pyi
philote_mdo/generated/data_pb2_grpc.py
philote_mdo/generated/disciplines_pb2.py
philote_mdo/generated/disciplines_pb2.pyi
philote_mdo/generated/disciplines_pb2_grpc.py
philote_mdo/openmdao/__init__.py
philote_mdo/openmdao/explicit.py
philote_mdo/openmdao/group.py
philote_mdo/openmdao/implicit.py
philote_mdo/openmdao/utils.py
philote_mdo/tests/__init__.py
philote_mdo/tests/test_discipline.py
philote_mdo/tests/test_discipline_client.py
philote_mdo/tests/test_discipline_server.py
philote_mdo/tests/test_explicit_client.py
philote_mdo/tests/test_explicit_server.py
philote_mdo/tests/test_implicit_client.py
philote_mdo/tests/test_implicit_server.py
philote_mdo/tests/test_integration.py
philote_mdo/tests/test_paraboloid.py
philote_mdo/tests/test_quadratic.py
philote_mdo/tests/test_rosenbrock.py
philote_mdo/tests/test_utils.py
philote_mdo/utils/__init__.py
philote_mdo/utils/helper.py
philote_mdo/utils/pair_dict.py
proto/.git
proto/.gitignore
proto/LICENSE
proto/README.md
proto/data.proto
proto/disciplines.proto
philote_mdo-0.5.1.dist-info/LICENSE
philote_mdo-0.5.1.dist-info/METADATA
philote_mdo-0.5.1.dist-info/WHEEL
philote_mdo-0.5.1.dist-info/RECORD
