Metadata-Version: 2.1
Name: philote-mdo
Version: 0.5.1
Summary: Python bindings that implement the Philote-MDO standard.
Home-page: https://chrislupp.github.io/Philote-Python/
License: Apache-2.0
Keywords: mdo,optimization,rpc
Author: Christopher Lupp
Requires-Python: >=3.9,<4.0
Classifier: License :: OSI Approved :: Apache Software License
Classifier: Programming Language :: Python :: 3
Classifier: Programming Language :: Python :: 3.9
Classifier: Programming Language :: Python :: 3.10
Classifier: Programming Language :: Python :: 3.11
Classifier: Programming Language :: Python :: 3.12
Requires-Dist: grpcio (>=1.62.0,<2.0.0)
Requires-Dist: numpy (>=1.26.4,<2.0.0)
Requires-Dist: scipy (>=1.12.0,<2.0.0)
Project-URL: Documentation, https://chrislupp.github.io/Philote-Python/
Project-URL: Repository, https://github.com/chrislupp/Philote-Python
